{
  "code": "E00005041",
  "name": "E00005041",
  "type": "oa",
  "area": 2.82,
  "count": 181408,
  "parents": [
    {
      "code": "E01001009",
      "name": "Croydon 019C",
      "type": "lsoa"
    },
    {
      "code": "E02000212",
      "name": "Croydon 019",
      "type": "msoa"
    },
    {
      "code": "E09000008",
      "name": "Croydon",
      "type": "lad"
    },
    {
      "code": "E12000007",
      "name": "London",
      "type": "rgn"
    },
    {
      "code": "E92000001",
      "name": "England",
      "type": "ctry"
    },
    {
      "code": "K04000001",
      "name": "England and Wales",
      "type": "ew"
    }
  ],
  "children": [],
  "bounds": [
    [
      -0.1142,
      51.38502
    ],
    [
      -0.11047,
      51.3872
    ]
  ],
  "data": {
    "population": {
      "perc": {
        "2001": {
          "female": 50.0,
          "male": 50.0
        },
        "2011": {
          "female": 52.05,
          "male": 47.95
        },
        "change": {
          "female": 2.05,
          "male": -2.05
        }
      },
      "perc_rank": {
        "2001": {
          "female": 116529.0,
          "male": 50999.0
        },
        "2011": {
          "female": 63966.0,
          "male": 117184.0
        },
        "change": {
          "female": 33696.0,
          "male": 137514.0
        }
      },
      "value": {
        "2001": {
          "all": 358.0,
          "female": 179.0,
          "male": 179.0
        },
        "2011": {
          "all": 511.0,
          "female": 266.0,
          "male": 245.0
        },
        "change": {
          "all": 42.74,
          "female": 48.6,
          "male": 36.87
        }
      },
      "value_rank": {
        "2001": {
          "all": 19643.0,
          "female": 25421.0,
          "male": 17488.0
        },
        "2011": {
          "all": 3147.0,
          "female": 2351.0,
          "male": 4405.0
        },
        "change": {
          "all": 16248.0,
          "female": 14692.0,
          "male": 21112.0
        }
      }
    },
    "ethnicity": {
      "perc": {
        "2001": {
          "asian": 45.53,
          "black": 21.79,
          "mixed": 8.38,
          "other": 1.68,
          "white": 22.63
        },
        "2011": {
          "asian": 42.07,
          "black": 31.51,
          "mixed": 5.68,
          "other": 1.37,
          "white": 19.37
        },
        "change": {
          "asian": -3.46,
          "black": 9.72,
          "mixed": -2.7,
          "other": -0.31,
          "white": -3.26
        }
      },
      "perc_rank": {
        "2001": {
          "asian": 2818.0,
          "black": 4050.0,
          "mixed": 884.0,
          "other": 11932.0,
          "white": 170265.0
        },
        "2011": {
          "asian": 5636.0,
          "black": 2850.0,
          "mixed": 14515.0,
          "other": 36258.0,
          "white": 179271.0
        },
        "change": {
          "asian": 168005.0,
          "black": 3798.0,
          "mixed": 169628.0,
          "other": 150901.0,
          "white": 104453.0
        }
      },
      "value": {
        "2001": {
          "all": 358.0,
          "asian": 163.0,
          "black": 78.0,
          "mixed": 30.0,
          "other": 6.0,
          "white": 81.0
        },
        "2011": {
          "all": 511.0,
          "asian": 215.0,
          "black": 161.0,
          "mixed": 29.0,
          "other": 7.0,
          "white": 99.0
        },
        "change": {
          "all": 42.74,
          "asian": 31.9,
          "black": 106.41,
          "mixed": -3.33,
          "other": 16.67,
          "white": 22.22
        }
      },
      "value_rank": {
        "2001": {
          "all": 19717.0,
          "asian": 2740.0,
          "black": 2750.0,
          "mixed": 442.0,
          "other": 7880.0,
          "white": 170258.0
        },
        "2011": {
          "all": 3147.0,
          "asian": 3465.0,
          "black": 671.0,
          "mixed": 3640.0,
          "other": 22147.0,
          "white": 176606.0
        },
        "change": {
          "all": 16272.0,
          "asian": 111548.0,
          "black": 72620.0,
          "mixed": 146077.0,
          "other": 74263.0,
          "white": 21365.0
        }
      }
    },
    "health": {
      "perc": {
        "2001": {
          "bad": 8.66,
          "fair": 23.46,
          "good": 67.88
        },
        "2011": {
          "bad": 3.91,
          "fair": 8.61,
          "good": 87.48
        },
        "change": {
          "bad": -4.75,
          "fair": -14.85,
          "good": 19.6
        }
      },
      "perc_rank": {
        "2001": {
          "bad": 84335.0,
          "fair": 70748.0,
          "good": 91832.0
        },
        "2011": {
          "bad": 117649.0,
          "fair": 155134.0,
          "good": 33354.0
        },
        "change": {
          "bad": 120673.0,
          "fair": 160769.0,
          "good": 11610.0
        }
      },
      "value": {
        "2001": {
          "all": 358.0,
          "bad": 31.0,
          "fair": 84.0,
          "good": 243.0
        },
        "2011": {
          "all": 511.0,
          "bad": 20.0,
          "fair": 44.0,
          "good": 447.0
        },
        "change": {
          "all": 42.74,
          "bad": -35.48,
          "fair": -47.62,
          "good": 83.95
        }
      },
      "value_rank": {
        "2001": {
          "all": 19643.0,
          "bad": 54408.0,
          "fair": 19607.0,
          "good": 34331.0
        },
        "2011": {
          "all": 3147.0,
          "bad": 56343.0,
          "fair": 68922.0,
          "good": 2522.0
        },
        "change": {
          "all": 16248.0,
          "bad": 90395.0,
          "fair": 137918.0,
          "good": 15497.0
        }
      }
    },
    "economic": {
      "perc": {
        "2001": {
          "employee": 52.63,
          "inactive": 31.58,
          "self-employed": 2.43,
          "student": 4.45,
          "unemployed": 8.91
        },
        "2011": {
          "employee": 51.79,
          "inactive": 33.06,
          "self-employed": 4.96,
          "student": 6.34,
          "unemployed": 3.86
        },
        "change": {
          "employee": -0.84,
          "inactive": 1.48,
          "self-employed": 2.53,
          "student": 1.89,
          "unemployed": -5.05
        }
      },
      "perc_rank": {
        "2001": {
          "employee": 83958.0,
          "inactive": 94190.0,
          "self-employed": 159186.0,
          "student": 14184.0,
          "unemployed": 7219.0
        },
        "2011": {
          "employee": 97086.0,
          "inactive": 63413.0,
          "self-employed": 154387.0,
          "student": 10453.0,
          "unemployed": 84451.0
        },
        "change": {
          "employee": 91248.0,
          "inactive": 40537.0,
          "self-employed": 59828.0,
          "student": 40337.0,
          "unemployed": 170331.0
        }
      },
      "value": {
        "2001": {
          "all": 247.0,
          "employee": 130.0,
          "inactive": 78.0,
          "self-employed": 6.0,
          "student": 11.0,
          "unemployed": 22.0
        },
        "2011": {
          "all": 363.0,
          "employee": 188.0,
          "inactive": 120.0,
          "self-employed": 18.0,
          "student": 23.0,
          "unemployed": 14.0
        },
        "change": {
          "all": 46.96,
          "employee": 44.62,
          "inactive": 53.85,
          "self-employed": 200.0,
          "student": 109.09,
          "unemployed": -36.36
        }
      },
      "value_rank": {
        "2001": {
          "all": 30774.0,
          "employee": 49280.0,
          "inactive": 55731.0,
          "self-employed": 149343.0,
          "student": 10142.0,
          "unemployed": 3043.0
        },
        "2011": {
          "all": 4249.0,
          "employee": 6443.0,
          "inactive": 5410.0,
          "self-employed": 99003.0,
          "student": 4859.0,
          "unemployed": 37729.0
        },
        "change": {
          "all": 15861.0,
          "employee": 21898.0,
          "inactive": 15392.0,
          "self-employed": 19274.0,
          "student": 58094.0,
          "unemployed": 161813.0
        }
      }
    },
    "travel": {
      "perc": {
        "2001": {
          "bicycle": 0.0,
          "bus": 8.06,
          "car_van": 50.0,
          "foot": 8.06,
          "home": 27.42,
          "moto": 0.0,
          "other": 0.0,
          "taxi": 0.0,
          "train_metro": 6.45
        },
        "2011": {
          "bicycle": 1.36,
          "bus": 22.73,
          "car_van": 24.09,
          "foot": 15.91,
          "home": 3.18,
          "moto": 0.45,
          "other": 1.36,
          "taxi": 0.0,
          "train_metro": 30.91
        },
        "change": {
          "bicycle": 1.36,
          "bus": 14.67,
          "car_van": -25.91,
          "foot": 7.85,
          "home": -24.24,
          "moto": 0.45,
          "other": 1.36,
          "taxi": 0.0,
          "train_metro": 24.46
        }
      },
      "perc_rank": {
        "2001": {
          "bicycle": 53831.0,
          "bus": 34882.0,
          "car_van": 84162.0,
          "foot": 84047.0,
          "home": 89079.0,
          "moto": 31335.0,
          "other": 19643.0,
          "taxi": 24059.0,
          "train_metro": 23627.0
        },
        "2011": {
          "bicycle": 111922.0,
          "bus": 10332.0,
          "car_van": 169563.0,
          "foot": 36770.0,
          "home": 111615.0,
          "moto": 109069.0,
          "other": 28791.0,
          "taxi": 78598.0,
          "train_metro": 15492.0
        },
        "change": {
          "bicycle": 76256.0,
          "bus": 13843.0,
          "car_van": 163783.0,
          "foot": 42034.0,
          "home": 88542.0,
          "moto": 86498.0,
          "other": 23781.0,
          "taxi": 64376.0,
          "train_metro": 10996.0
        }
      },
      "value": {
        "2001": {
          "all": 62.0,
          "bicycle": 0.0,
          "bus": 5.0,
          "car_van": 31.0,
          "foot": 5.0,
          "home": 17.0,
          "moto": 0.0,
          "other": 0.0,
          "taxi": 0.0,
          "train_metro": 4.0
        },
        "2011": {
          "all": 220.0,
          "bicycle": 3.0,
          "bus": 50.0,
          "car_van": 53.0,
          "foot": 35.0,
          "home": 7.0,
          "moto": 1.0,
          "other": 3.0,
          "taxi": 0.0,
          "train_metro": 68.0
        },
        "change": {
          "all": 254.84,
          "bicycle": Infinity,
          "bus": 900.0,
          "car_van": 70.97,
          "foot": 600.0,
          "home": -58.82,
          "moto": Infinity,
          "other": Infinity,
          "taxi": 0.0,
          "train_metro": 1600.0
        }
      },
      "value_rank": {
        "2001": {
          "all": 59266.0,
          "bicycle": 53831.0,
          "bus": 32024.0,
          "car_van": 61180.0,
          "foot": 66668.0,
          "home": 33525.0,
          "moto": 31335.0,
          "other": 19643.0,
          "taxi": 24059.0,
          "train_metro": 19302.0
        },
        "2011": {
          "all": 8791.0,
          "bicycle": 71979.0,
          "bus": 1833.0,
          "car_van": 149320.0,
          "foot": 12091.0,
          "home": 70925.0,
          "moto": 56271.0,
          "other": 6543.0,
          "taxi": 78598.0,
          "train_metro": 7450.0
        },
        "change": {
          "all": 96788.0,
          "bicycle": 1.0,
          "bus": 102031.0,
          "car_van": 136628.0,
          "foot": 76363.0,
          "home": 127041.0,
          "moto": 1.0,
          "other": 1.0,
          "taxi": 66404.0,
          "train_metro": 116800.0
        }
      }
    },
    "tenure": {
      "perc": {
        "2001": {
          "owned": 58.06,
          "rent_free": 0.0,
          "rented_private": 15.32,
          "rented_social": 24.19,
          "shared_ownership": 2.42
        },
        "2011": {
          "owned": 35.71,
          "rent_free": 0.6,
          "rented_private": 17.86,
          "rented_social": 30.36,
          "shared_ownership": 15.48
        },
        "change": {
          "owned": -22.35,
          "rent_free": 0.6,
          "rented_private": 2.54,
          "rented_social": 6.17,
          "shared_ownership": 13.06
        }
      },
      "perc_rank": {
        "2001": {
          "owned": 118220.0,
          "rent_free": 96960.0,
          "rented_private": 33565.0,
          "rented_social": 52395.0,
          "shared_ownership": 13644.0
        },
        "2011": {
          "owned": 152676.0,
          "rent_free": 128128.0,
          "rented_private": 56842.0,
          "rented_social": 42295.0,
          "shared_ownership": 969.0
        },
        "change": {
          "owned": 168460.0,
          "rent_free": 51564.0,
          "rented_private": 119367.0,
          "rented_social": 7641.0,
          "shared_ownership": 203.0
        }
      },
      "value": {
        "2001": {
          "all": 124.0,
          "owned": 72.0,
          "rent_free": 0.0,
          "rented_private": 19.0,
          "rented_social": 30.0,
          "shared_ownership": 3.0
        },
        "2011": {
          "all": 168.0,
          "owned": 60.0,
          "rent_free": 1.0,
          "rented_private": 30.0,
          "rented_social": 51.0,
          "shared_ownership": 26.0
        },
        "change": {
          "all": 35.48,
          "owned": -16.67,
          "rent_free": Infinity,
          "rented_private": 57.89,
          "rented_social": 70.0,
          "shared_ownership": 766.67
        }
      },
      "value_rank": {
        "2001": {
          "all": 87682.0,
          "owned": 114618.0,
          "rent_free": 96960.0,
          "rented_private": 32210.0,
          "rented_social": 51952.0,
          "shared_ownership": 6310.0
        },
        "2011": {
          "all": 10131.0,
          "owned": 131031.0,
          "rent_free": 79421.0,
          "rented_private": 39331.0,
          "rented_social": 29501.0,
          "shared_ownership": 578.0
        },
        "change": {
          "all": 16945.0,
          "owned": 158304.0,
          "rent_free": 1.0,
          "rented_private": 115779.0,
          "rented_social": 44342.0,
          "shared_ownership": 45365.0
        }
      }
    },
    "density": {
      "value": {
        "2001": {
          "all": 126.95
        },
        "2011": {
          "all": 181.21
        },
        "change": {
          "all": 42.74
        }
      },
      "value_rank": {
        "2001": {
          "all": 10056.0
        },
        "2011": {
          "all": 5970.0
        },
        "change": {
          "all": 16252.0
        }
      }
    },
    "age10yr": {
      "perc": {
        "2001": {
          "0-9": 18.26,
          "10-19": 10.35,
          "20-29": 19.07,
          "30-39": 17.98,
          "40-49": 13.62,
          "50-59": 8.17,
          "60-69": 6.54,
          "70-79": 2.45,
          "80plus": 3.54
        },
        "2011": {
          "0-9": 17.03,
          "10-19": 16.63,
          "20-29": 17.42,
          "30-39": 18.79,
          "40-49": 14.48,
          "50-59": 6.65,
          "60-69": 5.09,
          "70-79": 0.98,
          "80plus": 2.94
        },
        "change": {
          "0-9": -1.23,
          "10-19": 6.28,
          "20-29": -1.65,
          "30-39": 0.81,
          "40-49": 0.86,
          "50-59": -1.52,
          "60-69": -1.45,
          "70-79": -1.47,
          "80plus": -0.6
        }
      },
      "perc_rank": {
        "2001": {
          "0-9": 15534.0,
          "10-19": 116183.0,
          "20-29": 21631.0,
          "30-39": 45487.0,
          "40-49": 78418.0,
          "50-59": 143707.0,
          "60-69": 127891.0,
          "70-79": 124335.0,
          "80plus": 135534.0
        },
        "2011": {
          "0-9": 20933.0,
          "10-19": 17551.0,
          "20-29": 34836.0,
          "30-39": 24450.0,
          "40-49": 94558.0,
          "50-59": 169139.0,
          "60-69": 159718.0,
          "70-79": 167899.0,
          "80plus": 150899.0
        },
        "change": {
          "0-9": 97142.0,
          "10-19": 6229.0,
          "20-29": 120332.0,
          "30-39": 33148.0,
          "40-49": 94662.0,
          "50-59": 107880.0,
          "60-69": 134207.0,
          "70-79": 128553.0,
          "80plus": 109571.0
        }
      },
      "value": {
        "2001": {
          "0-9": 67.0,
          "10-19": 38.0,
          "20-29": 70.0,
          "30-39": 66.0,
          "40-49": 50.0,
          "50-59": 30.0,
          "60-69": 24.0,
          "70-79": 9.0,
          "80plus": 13.0,
          "all": 367.0
        },
        "2011": {
          "0-9": 87.0,
          "10-19": 85.0,
          "20-29": 89.0,
          "30-39": 96.0,
          "40-49": 74.0,
          "50-59": 34.0,
          "60-69": 26.0,
          "70-79": 5.0,
          "80plus": 15.0,
          "all": 511.0
        },
        "change": {
          "0-9": 29.85,
          "10-19": 123.68,
          "20-29": 27.14,
          "30-39": 45.45,
          "40-49": 48.0,
          "50-59": 13.33,
          "60-69": 8.33,
          "70-79": -44.44,
          "80plus": 15.38,
          "all": 39.24
        }
      },
      "value_rank": {
        "2001": {
          "0-9": 9015.0,
          "10-19": 74259.0,
          "20-29": 9978.0,
          "30-39": 17818.0,
          "40-49": 34293.0,
          "50-59": 111080.0,
          "60-69": 98500.0,
          "70-79": 101076.0,
          "80plus": 119287.0,
          "all": 15386.0
        },
        "2011": {
          "0-9": 3614.0,
          "10-19": 2883.0,
          "20-29": 9787.0,
          "30-39": 2996.0,
          "40-49": 6827.0,
          "50-59": 102245.0,
          "60-69": 115159.0,
          "70-79": 149030.0,
          "80plus": 118299.0,
          "all": 3147.0
        },
        "change": {
          "0-9": 52074.0,
          "10-19": 16548.0,
          "20-29": 66856.0,
          "30-39": 23435.0,
          "40-49": 47878.0,
          "50-59": 77175.0,
          "60-69": 116866.0,
          "70-79": 155348.0,
          "80plus": 87447.0,
          "all": 17547.0
        }
      }
    },
    "agemed": {
      "value": {
        "2001": {
          "all": 30.0
        },
        "2011": {
          "all": 29.0
        },
        "change": {
          "all": -3.33
        }
      },
      "value_rank": {
        "2001": {
          "all": 150452.0
        },
        "2011": {
          "all": 163500.0
        },
        "change": {
          "all": 144924.0
        }
      }
    }
  }
}