{
  "code": "E00153522",
  "name": "E00153522",
  "type": "oa",
  "area": 3.6,
  "count": 181408,
  "parents": [
    {
      "code": "E01030114",
      "name": "St Edmundsbury 014F",
      "type": "lsoa"
    },
    {
      "code": "E02006286",
      "name": "St Edmundsbury 014",
      "type": "msoa"
    },
    {
      "code": "E07000245",
      "name": "West Suffolk",
      "type": "lad"
    },
    {
      "code": "E10000029",
      "name": "Suffolk",
      "type": "cty"
    },
    {
      "code": "E12000006",
      "name": "East",
      "type": "rgn"
    },
    {
      "code": "E92000001",
      "name": "England",
      "type": "ctry"
    },
    {
      "code": "K04000001",
      "name": "England and Wales",
      "type": "ew"
    }
  ],
  "children": [],
  "bounds": [
    [
      0.42704,
      52.0768
    ],
    [
      0.4328,
      52.07871
    ]
  ],
  "data": {
    "population": {
      "perc": {
        "2001": {
          "female": 50.26,
          "male": 49.74
        },
        "2011": {
          "female": 45.0,
          "male": 55.0
        },
        "change": {
          "female": -5.26,
          "male": 5.26
        }
      },
      "perc_rank": {
        "2001": {
          "female": 112424.0,
          "male": 58821.0
        },
        "2011": {
          "female": 174241.0,
          "male": 7125.0
        },
        "change": {
          "female": 160125.0,
          "male": 11207.0
        }
      },
      "value": {
        "2001": {
          "all": 390.0,
          "female": 196.0,
          "male": 194.0
        },
        "2011": {
          "all": 400.0,
          "female": 180.0,
          "male": 220.0
        },
        "change": {
          "all": 2.56,
          "female": -8.16,
          "male": 13.4
        }
      },
      "value_rank": {
        "2001": {
          "all": 7905.0,
          "female": 10172.0,
          "male": 7727.0
        },
        "2011": {
          "all": 16411.0,
          "female": 38401.0,
          "male": 8828.0
        },
        "change": {
          "all": 91884.0,
          "female": 150865.0,
          "male": 53757.0
        }
      }
    },
    "ethnicity": {
      "perc": {
        "2001": {
          "asian": 0.0,
          "black": 0.76,
          "mixed": 2.78,
          "other": 0.0,
          "white": 96.46
        },
        "2011": {
          "asian": 1.0,
          "black": 1.25,
          "mixed": 1.25,
          "other": 0.75,
          "white": 95.75
        },
        "change": {
          "asian": 1.0,
          "black": 0.49,
          "mixed": -1.53,
          "other": 0.75,
          "white": -0.71
        }
      },
      "perc_rank": {
        "2001": {
          "asian": 98706.0,
          "black": 63327.0,
          "mixed": 23629.0,
          "other": 38685.0,
          "white": 102063.0
        },
        "2011": {
          "asian": 114951.0,
          "black": 65628.0,
          "mixed": 97342.0,
          "other": 50938.0,
          "white": 86066.0
        },
        "change": {
          "asian": 76957.0,
          "black": 60004.0,
          "mixed": 163822.0,
          "other": 36408.0,
          "white": 53610.0
        }
      },
      "value": {
        "2001": {
          "all": 395.0,
          "asian": 0.0,
          "black": 3.0,
          "mixed": 11.0,
          "other": 0.0,
          "white": 381.0
        },
        "2011": {
          "all": 400.0,
          "asian": 4.0,
          "black": 5.0,
          "mixed": 5.0,
          "other": 3.0,
          "white": 383.0
        },
        "change": {
          "all": 1.27,
          "asian": null,
          "black": 66.67,
          "mixed": -54.55,
          "other": null,
          "white": 0.52
        }
      },
      "value_rank": {
        "2001": {
          "all": 6976.0,
          "asian": 98706.0,
          "black": 41872.0,
          "mixed": 12871.0,
          "other": 38685.0,
          "white": 4979.0
        },
        "2011": {
          "all": 16411.0,
          "asian": 101119.0,
          "black": 54797.0,
          "mixed": 74846.0,
          "other": 41351.0,
          "white": 9057.0
        },
        "change": {
          "all": 100230.0,
          "asian": 1.0,
          "black": 77804.0,
          "mixed": 164184.0,
          "other": 1.0,
          "white": 75740.0
        }
      }
    },
    "health": {
      "perc": {
        "2001": {
          "bad": 6.92,
          "fair": 25.38,
          "good": 67.69
        },
        "2011": {
          "bad": 5.0,
          "fair": 10.75,
          "good": 84.25
        },
        "change": {
          "bad": -1.92,
          "fair": -14.63,
          "good": 16.56
        }
      },
      "perc_rank": {
        "2001": {
          "bad": 113969.0,
          "fair": 46436.0,
          "good": 93313.0
        },
        "2011": {
          "bad": 90504.0,
          "fair": 128120.0,
          "good": 63551.0
        },
        "change": {
          "bad": 48302.0,
          "fair": 159617.0,
          "good": 31016.0
        }
      },
      "value": {
        "2001": {
          "all": 390.0,
          "bad": 27.0,
          "fair": 99.0,
          "good": 264.0
        },
        "2011": {
          "all": 400.0,
          "bad": 20.0,
          "fair": 43.0,
          "good": 337.0
        },
        "change": {
          "all": 2.56,
          "bad": -25.93,
          "fair": -56.57,
          "good": 27.65
        }
      },
      "value_rank": {
        "2001": {
          "all": 7905.0,
          "bad": 73407.0,
          "fair": 4361.0,
          "good": 18778.0
        },
        "2011": {
          "all": 16411.0,
          "bad": 56343.0,
          "fair": 73886.0,
          "good": 16538.0
        },
        "change": {
          "all": 91885.0,
          "bad": 64416.0,
          "fair": 165443.0,
          "good": 71460.0
        }
      }
    },
    "economic": {
      "perc": {
        "2001": {
          "employee": 59.67,
          "inactive": 31.69,
          "self-employed": 2.47,
          "student": 1.65,
          "unemployed": 4.53
        },
        "2011": {
          "employee": 59.71,
          "inactive": 26.74,
          "self-employed": 6.59,
          "student": 1.83,
          "unemployed": 5.13
        },
        "change": {
          "employee": 0.04,
          "inactive": -4.95,
          "self-employed": 4.12,
          "student": 0.18,
          "unemployed": 0.6
        }
      },
      "perc_rank": {
        "2001": {
          "employee": 41158.0,
          "inactive": 93440.0,
          "self-employed": 158884.0,
          "student": 113390.0,
          "unemployed": 43222.0
        },
        "2011": {
          "employee": 40090.0,
          "inactive": 116190.0,
          "self-employed": 130025.0,
          "student": 130507.0,
          "unemployed": 57124.0
        },
        "change": {
          "employee": 81496.0,
          "inactive": 109252.0,
          "self-employed": 30758.0,
          "student": 99992.0,
          "unemployed": 94756.0
        }
      },
      "value": {
        "2001": {
          "all": 243.0,
          "employee": 145.0,
          "inactive": 77.0,
          "self-employed": 6.0,
          "student": 4.0,
          "unemployed": 11.0
        },
        "2011": {
          "all": 273.0,
          "employee": 163.0,
          "inactive": 73.0,
          "self-employed": 18.0,
          "student": 5.0,
          "unemployed": 14.0
        },
        "change": {
          "all": 12.35,
          "employee": 12.41,
          "inactive": -5.19,
          "self-employed": 200.0,
          "student": 25.0,
          "unemployed": 27.27
        }
      },
      "value_rank": {
        "2001": {
          "all": 35672.0,
          "employee": 27259.0,
          "inactive": 58551.0,
          "self-employed": 149343.0,
          "student": 81637.0,
          "unemployed": 29173.0
        },
        "2011": {
          "all": 26251.0,
          "employee": 17557.0,
          "inactive": 61572.0,
          "self-employed": 99003.0,
          "student": 97422.0,
          "unemployed": 37729.0
        },
        "change": {
          "all": 54818.0,
          "employee": 65585.0,
          "inactive": 100197.0,
          "self-employed": 19274.0,
          "student": 100114.0,
          "unemployed": 105557.0
        }
      }
    },
    "travel": {
      "perc": {
        "2001": {
          "bicycle": 0.0,
          "bus": 0.0,
          "car_van": 44.44,
          "foot": 0.0,
          "home": 55.56,
          "moto": 0.0,
          "other": 0.0,
          "taxi": 0.0,
          "train_metro": 0.0
        },
        "2011": {
          "bicycle": 4.84,
          "bus": 4.3,
          "car_van": 62.9,
          "foot": 25.27,
          "home": 1.61,
          "moto": 0.0,
          "other": 0.54,
          "taxi": 0.54,
          "train_metro": 0.0
        },
        "change": {
          "bicycle": 4.84,
          "bus": 4.3,
          "car_van": 18.46,
          "foot": 25.27,
          "home": -53.95,
          "moto": 0.0,
          "other": 0.54,
          "taxi": 0.54,
          "train_metro": 0.0
        }
      },
      "perc_rank": {
        "2001": {
          "bicycle": 53831.0,
          "bus": 74758.0,
          "car_van": 106314.0,
          "foot": 111228.0,
          "home": 23342.0,
          "moto": 31335.0,
          "other": 19643.0,
          "taxi": 24059.0,
          "train_metro": 45401.0
        },
        "2011": {
          "bicycle": 30586.0,
          "bus": 102370.0,
          "car_van": 111537.0,
          "foot": 12001.0,
          "home": 152316.0,
          "moto": 111520.0,
          "other": 88417.0,
          "taxi": 70427.0,
          "train_metro": 157075.0
        },
        "change": {
          "bicycle": 18634.0,
          "bus": 64260.0,
          "car_van": 71851.0,
          "foot": 2856.0,
          "home": 153021.0,
          "moto": 89728.0,
          "other": 74866.0,
          "taxi": 56715.0,
          "train_metro": 137531.0
        }
      },
      "value": {
        "2001": {
          "all": 18.0,
          "bicycle": 0.0,
          "bus": 0.0,
          "car_van": 8.0,
          "foot": 0.0,
          "home": 10.0,
          "moto": 0.0,
          "other": 0.0,
          "taxi": 0.0,
          "train_metro": 0.0
        },
        "2011": {
          "all": 186.0,
          "bicycle": 9.0,
          "bus": 8.0,
          "car_van": 117.0,
          "foot": 47.0,
          "home": 3.0,
          "moto": 0.0,
          "other": 1.0,
          "taxi": 1.0,
          "train_metro": 0.0
        },
        "change": {
          "all": 933.33,
          "bicycle": null,
          "bus": null,
          "car_van": 1362.5,
          "foot": null,
          "home": -70.0,
          "moto": 0.0,
          "other": null,
          "taxi": null,
          "train_metro": 0.0
        }
      },
      "value_rank": {
        "2001": {
          "all": 141293.0,
          "bicycle": 53831.0,
          "bus": 74758.0,
          "car_van": 129866.0,
          "foot": 111228.0,
          "home": 88183.0,
          "moto": 31335.0,
          "other": 19643.0,
          "taxi": 24059.0,
          "train_metro": 45401.0
        },
        "2011": {
          "all": 28118.0,
          "bicycle": 18131.0,
          "bus": 81954.0,
          "car_van": 44457.0,
          "foot": 5372.0,
          "home": 127167.0,
          "moto": 111520.0,
          "other": 42316.0,
          "taxi": 32746.0,
          "train_metro": 157075.0
        },
        "change": {
          "all": 21952.0,
          "bicycle": 1.0,
          "bus": 1.0,
          "car_van": 33962.0,
          "foot": 1.0,
          "home": 146952.0,
          "moto": 93061.0,
          "other": 1.0,
          "taxi": 1.0,
          "train_metro": 146169.0
        }
      }
    },
    "tenure": {
      "perc": {
        "2001": {
          "owned": 39.69,
          "rent_free": 2.29,
          "rented_private": 0.0,
          "rented_social": 58.02,
          "shared_ownership": 0.0
        },
        "2011": {
          "owned": 44.27,
          "rent_free": 0.0,
          "rented_private": 16.03,
          "rented_social": 39.69,
          "shared_ownership": 0.0
        },
        "change": {
          "owned": 4.58,
          "rent_free": -2.29,
          "rented_private": 16.03,
          "rented_social": -18.33,
          "shared_ownership": 0.0
        }
      },
      "perc_rank": {
        "2001": {
          "owned": 144580.0,
          "rent_free": 78779.0,
          "rented_private": 151994.0,
          "rented_social": 15966.0,
          "shared_ownership": 32535.0
        },
        "2011": {
          "owned": 139286.0,
          "rent_free": 130555.0,
          "rented_private": 64644.0,
          "rented_social": 30538.0,
          "shared_ownership": 62908.0
        },
        "change": {
          "owned": 15818.0,
          "rent_free": 136689.0,
          "rented_private": 12116.0,
          "rented_social": 169529.0,
          "shared_ownership": 43402.0
        }
      },
      "value": {
        "2001": {
          "all": 131.0,
          "owned": 52.0,
          "rent_free": 3.0,
          "rented_private": 0.0,
          "rented_social": 76.0,
          "shared_ownership": 0.0
        },
        "2011": {
          "all": 131.0,
          "owned": 58.0,
          "rent_free": 0.0,
          "rented_private": 21.0,
          "rented_social": 52.0,
          "shared_ownership": 0.0
        },
        "change": {
          "all": 0.0,
          "owned": 11.54,
          "rent_free": -100.0,
          "rented_private": null,
          "rented_social": -31.58,
          "shared_ownership": 0.0
        }
      },
      "value_rank": {
        "2001": {
          "all": 46026.0,
          "owned": 139457.0,
          "rent_free": 42416.0,
          "rented_private": 151994.0,
          "rented_social": 13220.0,
          "shared_ownership": 32535.0
        },
        "2011": {
          "all": 68870.0,
          "owned": 133924.0,
          "rent_free": 130555.0,
          "rented_private": 60966.0,
          "rented_social": 28552.0,
          "shared_ownership": 62908.0
        },
        "change": {
          "all": 107796.0,
          "owned": 35147.0,
          "rent_free": 163174.0,
          "rented_private": 1.0,
          "rented_social": 147847.0,
          "shared_ownership": 47512.0
        }
      }
    },
    "density": {
      "value": {
        "2001": {
          "all": 108.33
        },
        "2011": {
          "all": 111.11
        },
        "change": {
          "all": 2.57
        }
      },
      "value_rank": {
        "2001": {
          "all": 14606.0
        },
        "2011": {
          "all": 18351.0
        },
        "change": {
          "all": 91760.0
        }
      }
    },
    "age10yr": {
      "perc": {
        "2001": {
          "0-9": 22.84,
          "10-19": 18.02,
          "20-29": 17.01,
          "30-39": 16.24,
          "40-49": 11.42,
          "50-59": 5.58,
          "60-69": 4.06,
          "70-79": 2.28,
          "80plus": 2.54
        },
        "2011": {
          "0-9": 16.25,
          "10-19": 19.25,
          "20-29": 17.0,
          "30-39": 17.25,
          "40-49": 12.0,
          "50-59": 8.25,
          "60-69": 4.75,
          "70-79": 2.0,
          "80plus": 3.25
        },
        "change": {
          "0-9": -6.59,
          "10-19": 1.23,
          "20-29": -0.01,
          "30-39": 1.01,
          "40-49": 0.58,
          "50-59": 2.67,
          "60-69": 0.69,
          "70-79": -0.28,
          "80plus": 0.71
        }
      },
      "perc_rank": {
        "2001": {
          "0-9": 3436.0,
          "10-19": 13560.0,
          "20-29": 29924.0,
          "30-39": 67410.0,
          "40-49": 122127.0,
          "50-59": 163032.0,
          "60-69": 156342.0,
          "70-79": 128607.0,
          "80plus": 149406.0
        },
        "2011": {
          "0-9": 26237.0,
          "10-19": 5789.0,
          "20-29": 37347.0,
          "30-39": 33813.0,
          "40-49": 143004.0,
          "50-59": 155422.0,
          "60-69": 162721.0,
          "70-79": 142623.0,
          "80plus": 146411.0
        },
        "change": {
          "0-9": 161873.0,
          "10-19": 53303.0,
          "20-29": 92714.0,
          "30-39": 31001.0,
          "40-49": 99536.0,
          "50-59": 42462.0,
          "60-69": 102216.0,
          "70-79": 95738.0,
          "80plus": 78596.0
        }
      },
      "value": {
        "2001": {
          "0-9": 90.0,
          "10-19": 71.0,
          "20-29": 67.0,
          "30-39": 64.0,
          "40-49": 45.0,
          "50-59": 22.0,
          "60-69": 16.0,
          "70-79": 9.0,
          "80plus": 10.0,
          "all": 394.0
        },
        "2011": {
          "0-9": 65.0,
          "10-19": 77.0,
          "20-29": 68.0,
          "30-39": 69.0,
          "40-49": 48.0,
          "50-59": 33.0,
          "60-69": 19.0,
          "70-79": 8.0,
          "80plus": 13.0,
          "all": 400.0
        },
        "change": {
          "0-9": -27.78,
          "10-19": 8.45,
          "20-29": 1.49,
          "30-39": 7.81,
          "40-49": 6.67,
          "50-59": 50.0,
          "60-69": 18.75,
          "70-79": -11.11,
          "80plus": 30.0,
          "all": 1.52
        }
      },
      "value_rank": {
        "2001": {
          "0-9": 1955.0,
          "10-19": 6025.0,
          "20-29": 11584.0,
          "30-39": 21134.0,
          "40-49": 53078.0,
          "50-59": 144296.0,
          "60-69": 138574.0,
          "70-79": 101076.0,
          "80plus": 135769.0,
          "all": 7149.0
        },
        "2011": {
          "0-9": 13577.0,
          "10-19": 4721.0,
          "20-29": 20008.0,
          "30-39": 15421.0,
          "40-49": 69484.0,
          "50-59": 107991.0,
          "60-69": 146434.0,
          "70-79": 118272.0,
          "80plus": 128937.0,
          "all": 16411.0
        },
        "change": {
          "0-9": 144139.0,
          "10-19": 78009.0,
          "20-29": 104962.0,
          "30-39": 52419.0,
          "40-49": 111152.0,
          "50-59": 36675.0,
          "60-69": 101841.0,
          "70-79": 114059.0,
          "80plus": 69924.0,
          "all": 99044.0
        }
      }
    },
    "agemed": {
      "value": {
        "2001": {
          "all": 25.0
        },
        "2011": {
          "all": 28.0
        },
        "change": {
          "all": 12.0
        }
      },
      "value_rank": {
        "2001": {
          "all": 166821.0
        },
        "2011": {
          "all": 168212.0
        },
        "change": {
          "all": 44769.0
        }
      }
    }
  }
}